README.md
setup.cfg
setup.py
aetros/JobModel.py
aetros/KerasCallback.py
aetros/MonitorThread.py
aetros/Trainer.py
aetros/__init__.py
aetros/__main__.py
aetros/api.py
aetros/auto_dataset.py
aetros/backend.py
aetros/client.py
aetros/const.py
aetros/cuda_gpu.py
aetros/git-sync.py
aetros/git.py
aetros/keras.py
aetros/keras_model_utils.py
aetros/logger.py
aetros/predict.py
aetros/starter.py
aetros.egg-info/PKG-INFO
aetros.egg-info/SOURCES.txt
aetros.egg-info/dependency_links.txt
aetros.egg-info/entry_points.txt
aetros.egg-info/requires.txt
aetros.egg-info/top_level.txt
aetros/commands/AddCommand.py
aetros/commands/ApiCommand.py
aetros/commands/AuthenticateCommand.py
aetros/commands/GPUCommand.py
aetros/commands/HomeConfigCommand.py
aetros/commands/IdCommand.py
aetros/commands/InitCommand.py
aetros/commands/JobCatCommand.py
aetros/commands/JobCheckoutCommand.py
aetros/commands/JobCommitsCommand.py
aetros/commands/JobDiffCommand.py
aetros/commands/JobFilesCommand.py
aetros/commands/JobPullCommand.py
aetros/commands/JobPushCommand.py
aetros/commands/JobsCommand.py
aetros/commands/ModelCommand.py
aetros/commands/PredictCommand.py
aetros/commands/PredictionServerCommand.py
aetros/commands/RunCommand.py
aetros/commands/ServerCommand.py
aetros/commands/StartCommand.py
aetros/commands/StartSimpleCommand.py
aetros/commands/__init__.py
aetros/tests/__init__.py
aetros/tests/aetros_api_test.py
aetros/tests/aetros_config_test.py
aetros/tests/aetros_dataset_test.py
aetros/tests/aetros_keras_test.py
aetros/tests/aetros_parameter_extract_test.py
aetros/tests/aetros_parameter_lose_test.py
aetros/tests/image_test.py
aetros/utils/__init__.py
aetros/utils/git.py
aetros/utils/image.py
aetros/utils/pilutil.py
test/test.py