Metadata-Version: 1.1
Name: aetros
Version: 0.14.8
Summary: Python SDK for aetros.com
Home-page: https://github.com/aetros/aetros-cli
Author: Marc J. Schmidt
Author-email: marc@marcjschmidt.de
License: MIT
Download-URL: https://github.com/aetros/aetros-cli/tarball/0.14.8
Platform: UNKNOWN
